treepy/__init__.py
treepy/main.py
mytreepy-0.2.dist-info/METADATA
mytreepy-0.2.dist-info/WHEEL
mytreepy-0.2.dist-info/entry_points.txt
mytreepy-0.2.dist-info/top_level.txt
mytreepy-0.2.dist-info/RECORD
